sample_datasets/__init__.py
sample_datasets/_geonames.py
sample_datasets/tests/__init__.py
sample_datasets/tests/test_main.py
sample_datasets-0.1.0.dist-info/METADATA
sample_datasets-0.1.0.dist-info/WHEEL
sample_datasets-0.1.0.dist-info/entry_points.txt
sample_datasets-0.1.0.dist-info/top_level.txt
sample_datasets-0.1.0.dist-info/RECORD
