Metadata-Version: 2.1
Name: sample-datasets
Version: 0.1.0
Summary: Sample datasets for Python dataframe libraries
Classifier: Development Status :: 4 - Beta
Classifier: Programming Language :: Python
Requires-Dist: pyarrow
